wcpan.logger-1.5.0-py3.9-nspkg.pth
wcpan/logger/__init__.py
wcpan/logger/log.py
wcpan.logger-1.5.0.dist-info/LICENSE
wcpan.logger-1.5.0.dist-info/METADATA
wcpan.logger-1.5.0.dist-info/WHEEL
wcpan.logger-1.5.0.dist-info/namespace_packages.txt
wcpan.logger-1.5.0.dist-info/top_level.txt
wcpan.logger-1.5.0.dist-info/RECORD
